dddex/__init__.py
dddex/_modidx.py
dddex/baseClasses.py
dddex/crossValidation.py
dddex/levelSetKDEx_multivariate.py
dddex/levelSetKDEx_univariate.py
dddex/loadData.py
dddex/utils.py
dddex/wSAA.py
dddex/datasets/dataBakery.csv
dddex/datasets/dataYaz.csv
dddex/datasets/dataYaz_multivariate.csv
dddex-0.0.40.dist-info/LICENSE
dddex-0.0.40.dist-info/METADATA
dddex-0.0.40.dist-info/WHEEL
dddex-0.0.40.dist-info/entry_points.txt
dddex-0.0.40.dist-info/top_level.txt
dddex-0.0.40.dist-info/RECORD
