Metadata-Version: 2.1
Name: dddex
Version: 0.0.40
Summary: The package 'data-driven density estimation x' (dddex) turns any standard point forecasting model into an estimator of the underlying conditional density
Home-page: https://github.com/kaiguender/dddex
Author: kaiguender
Author-email: kai.guender@yahoo.de
License: Apache Software License 2.0
Keywords: nbdev jupyter notebook python
Classifier: Development Status :: 4 - Beta
Classifier: Intended Audience :: Developers
Classifier: Natural Language :: English
Classifier: Programming Language :: Python :: 3.7
Classifier: Programming Language :: Python :: 3.8
Classifier: Programming Language :: Python :: 3.9
Classifier: Programming Language :: Python :: 3.10
Classifier: License :: OSI Approved :: Apache Software License
Requires-Python: >=3.7
License-File: LICENSE
Requires-Dist: fastcore >=1.5.27
Requires-Dist: pandas >=1.3.0
Requires-Dist: scikit-learn >=1.2.0
Requires-Dist: faiss-cpu >=1.7.1
Requires-Dist: lightgbm >=3.3.2
Requires-Dist: tabulate >=0.8.10
Provides-Extra: dev
